pika_multithreaded/__init__.py
pika_multithreaded/clients.py
pika_multithreaded/utils.py
pika_multithreaded-1.1.0.dist-info/LICENSE
pika_multithreaded-1.1.0.dist-info/METADATA
pika_multithreaded-1.1.0.dist-info/WHEEL
pika_multithreaded-1.1.0.dist-info/top_level.txt
pika_multithreaded-1.1.0.dist-info/RECORD
