Metadata-Version: 2.1
Name: pika-multithreaded
Version: 1.1.0
Summary: A project that enables multithreading support for the Pika package
Home-page: https://github.com/nimbis/pika-multithreaded
Author: Nimbis Services
Author-email: info@nimbisservics.com
Requires-Python: >=3.6
License-File: LICENSE
Requires-Dist: pika
